candl_lexer/__init__.py
candl_lexer/lexer.py
candl_lexer-0.0.3.dist-info/LICENSE
candl_lexer-0.0.3.dist-info/METADATA
candl_lexer-0.0.3.dist-info/WHEEL
candl_lexer-0.0.3.dist-info/entry_points.txt
candl_lexer-0.0.3.dist-info/top_level.txt
candl_lexer-0.0.3.dist-info/RECORD
