Metadata-Version: 2.1
Name: candl-lexer
Version: 0.0.3
Summary: Lexer for the CAnDL DSL
Home-page: https://github.com/Baltoli/candl-lexer
Author: Bruce Collie
Author-email: brucecollie82@gmail.com
License: UNKNOWN
Platform: UNKNOWN
Classifier: Programming Language :: Python :: 3
Classifier: License :: OSI Approved :: MIT License
Classifier: Operating System :: OS Independent
Requires-Python: >=3.6
License-File: LICENSE
Requires-Dist: pygments
